[
  {
    "title": "ofek test 5",
    "severity": "12",
    "description": "555555555555555555",
    "createdAt": 12,
    "label": "need-CR",
    "_id": "hpL3N"
  },
  {
    "_id": "abc123",
    "title": "Cannot save a Car",
    "description": "problem when clicking Save",
    "severity": 4,
    "createdAt": 1542107359454,
    "label": "dev-branch"
  },
  {
    "_id": "abc124",
    "title": "Cannot save a papar",
    "description": "problem when clicking remove",
    "severity": 3,
    "createdAt": 1542107359454,
    "label": "critical"
  },
  {
    "title": "test bug",
    "severity": 25,
    "description": "bug testing right now ",
    "createdAt": 1672751815043,
    "_id": "dOydD",
    "label": "need-CR"
  },
  {
    "title": "ooo",
    "severity": 6,
    "description": "aa\n",
    "createdAt": 1672752535251,
    "_id": "42Src",
    "label": "need-CR"
  },
  {
    "title": "test bug num 3 ",
    "severity": 25,
    "description": "bug testing right now ",
    "createdAt": 16727515043,
    "_id": "ydD",
    "label": "dev-branch"
  },
  {
    "title": "test bug num 6",
    "severity": 25,
    "description": "bug testing right now ",
    "createdAt": 1672751815,
    "_id": "dOy",
    "label": "dev-branch"
  },
  {
    "title": "test bug num 8 ",
    "severity": 25,
    "description": "bug testing right now ",
    "createdAt": 1672751815043,
    "_id": "dOydDaaaa",
    "label": "dev-branch"
  }
]